mshack/__init__.py
mshack-0.1.1.dist-info/licenses/LICENSE
mshack-0.1.1.dist-info/METADATA
mshack-0.1.1.dist-info/WHEEL
mshack-0.1.1.dist-info/top_level.txt
mshack-0.1.1.dist-info/RECORD
