Metadata-Version: 2.4
Name: mshack
Version: 0.1.1
Summary: Export music score sheets to PDF
Home-page: https://github.com/CaseyJohnson-RS/MSHack
Author: Casey Johnson
Author-email: sharus.programmer@gmail.com
Classifier: Development Status :: 3 - Alpha
Classifier: Intended Audience :: Developers
Classifier: License :: OSI Approved :: MIT License
Classifier: Programming Language :: Python :: 3.8
Classifier: Programming Language :: Python :: 3.9
Classifier: Programming Language :: Python :: 3.10
License-File: LICENSE
Requires-Dist: requests
Requires-Dist: selenium
Requires-Dist: svglib
Requires-Dist: pillow
Requires-Dist: reportlab
Dynamic: author
Dynamic: author-email
Dynamic: classifier
Dynamic: home-page
Dynamic: license-file
Dynamic: requires-dist
Dynamic: summary
